libheysops/__init__.py
libheysops/base.py
libheysops/heysops.py
heysops-0.0.1.dist-info/METADATA
heysops-0.0.1.dist-info/WHEEL
heysops-0.0.1.dist-info/entry_points.txt
heysops-0.0.1.dist-info/top_level.txt
heysops-0.0.1.dist-info/RECORD
