Metadata-Version: 2.1
Name: heysops
Version: 0.0.1
Summary: UNKNOWN
Home-page: UNKNOWN
Author: Chapin Bryce
Author-email: python@chapinb.com
License: MIT License
Keywords: sops,secrets
Platform: UNKNOWN
Classifier: License :: OSI Approved :: MIT License
Classifier: Programming Language :: Python :: 3
Classifier: Programming Language :: Python :: 3.6
Classifier: Programming Language :: Python :: 3.7
Classifier: Programming Language :: Python :: 3.8
Classifier: Programming Language :: Python :: 3.9
Requires-Dist: ruamel.yaml (==0.17.13)
Provides-Extra: dev
Requires-Dist: black ; extra == 'dev'
Requires-Dist: build ; extra == 'dev'
Requires-Dist: pyre-check ; extra == 'dev'
Requires-Dist: radon ; extra == 'dev'
Requires-Dist: setuptool ; extra == 'dev'
Requires-Dist: wheel ; extra == 'dev'
